AUTHORS
COPYING
MANIFEST.in
README.md
nullclient.py
setup.cfg
setup.py
welcome
debian/changelog
debian/compat
debian/control
debian/copyright
debian/pycompat
debian/rules
pypurple/account.pyx
pypurple/account_cbs.pxd
pypurple/blist_cbs.pxd
pypurple/buddy.pyx
pypurple/c_purple.c
pypurple/c_purple.h
pypurple/connection_cbs.pxd
pypurple/conversation.pyx
pypurple/conversation_cbs.pxd
pypurple/miniclient.pyx
pypurple/notify_cbs.pxd
pypurple/plugin.pyx
pypurple/protocol.pyx
pypurple/proxy.pyx
pypurple/pypurple.c
pypurple/pypurple.pyx
pypurple/request_cbs.pxd
pypurple/signal_cbs.pxd
pypurple/util.pxd
pypurple/util.pyx
pypurple.egg-info/PKG-INFO
pypurple.egg-info/SOURCES.txt
pypurple.egg-info/dependency_links.txt
pypurple.egg-info/top_level.txt
pypurple/libpurple/account.pxd
pypurple/libpurple/accountopt.pxd
pypurple/libpurple/blist.pxd
pypurple/libpurple/buddyicon.pxd
pypurple/libpurple/connection.pxd
pypurple/libpurple/conversation.pxd
pypurple/libpurple/core.pxd
pypurple/libpurple/debug.pxd
pypurple/libpurple/eventloop.pxd
pypurple/libpurple/ft.pxd
pypurple/libpurple/glib.pxd
pypurple/libpurple/idle.pxd
pypurple/libpurple/notify.pxd
pypurple/libpurple/plugin.pxd
pypurple/libpurple/pounce.pxd
pypurple/libpurple/prefs.pxd
pypurple/libpurple/privacy.pxd
pypurple/libpurple/proxy.pxd
pypurple/libpurple/prpl.pxd
pypurple/libpurple/pypurple.pxd
pypurple/libpurple/request.pxd
pypurple/libpurple/roomlist.pxd
pypurple/libpurple/savedstatuses.pxd
pypurple/libpurple/server.pxd
pypurple/libpurple/signals.pxd
pypurple/libpurple/status.pxd
pypurple/libpurple/util.pxd
pypurple/libpurple/value.pxd
pypurple/libpurple/xmlnode.pxd