Metadata-Version: 1.1
Name: pypurple
Version: 0.0.11
Summary: Python bindings for Purple
Home-page: https://github.com/anpetrov/python-purple
Author: Andrey Petrov
Author-email: andrey.petrov@gmail.com
License: UNKNOWN
Download-URL: https://github.com/anpetrov/python-purple/archive/0.0.1.tar.gz
Platform: UNKNOWN
